{"word_count": 654, "processed_language": "en", "personality": [{"trait_id": "big5_openness", "name": "Openness", "category": "personality", "percentile": 0.9748168094484246, "raw_score": 0.8111273814343696, "significant": true, "children": [{"trait_id": "facet_adventurousness", "name": "Adventurousness", "category": "personality", "percentile": 0.6148869795396337, "raw_score": 0.5152057455844941, "significant": true}, {"trait_id": "facet_artistic_interests", "name": "Artistic interests", "category": "personality", "percentile": 0.2584631539020467, "raw_score": 0.6325162087006677, "significant": true}, {"trait_id": "facet_emotionality", "name": "Emotionality", "category": "personality", "percentile": 0.04665519225950859, "raw_score": 0.5797773671543694, "significant": true}, {"trait_id": "facet_imagination", "name": "Imagination", "category": "personality", "percentile": 0.5363672482735012, "raw_score": 0.7393929186254119, "significant": true}, {"trait_id": "facet_intellect", "name": "Intellect", "category": "personality", "percentile": 0.9706478925588813, "raw_score": 0.6947479659374718, "significant": true}, {"trait_id": "facet_liberalism", "name": "Authority-challenging", "category": "personality", "percentile": 0.8446660009198671, "raw_score": 0.567291918622923, "significant": true}]}, {"trait_id": "big5_conscientiousness", "name": "Conscientiousness", "category": "personality", "percentile": 0.46542592773071173, "raw_score": 0.6240038323818141, "significant": true, "children": [{"trait_id": "facet_achievement_striving", "name": "Achievement striving", "category": "personality", "percentile": 0.5999402081370435, "raw_score": 0.7018035860503821, "significant": true}, {"trait_id": "facet_cautiousness", "name": "Cautiousness", "category": "personality", "percentile": 0.8919734402723876, "raw_score": 0.5705655855825282, "significant": true}, {"trait_id": "facet_dutifulness", "name": "Dutifulness", "category": "personality", "percentile": 0.4537303743843472, "raw_score": 0.6560536700350457, "significant": true}, {"trait_id": "facet_orderliness", "name": "Orderliness", "category": "personality", "percentile": 0.2868387980985889, "raw_score": 0.4757261141091201, "significant": true}, {"trait_id": "facet_self_discipline", "name": "Self-discipline", "category": "personality", "percentile": 0.44424837517276705, "raw_score": 0.5639745551690084, "significant": true}, {"trait_id": "facet_self_efficacy", "name": "Self-efficacy", "category": "personality", "percentile": 0.6591654576036894, "raw_score": 0.7675252456706233, "significant": true}]}, {"trait_id": "big5_extraversion", "name": "Extraversion", "category": "personality", "percentile": 0.04026194675838041, "raw_score": 0.4730195564103228, "significant": true, "children": [{"trait_id": "facet_activity_level", "name": "Activity level", "category": "personality", "percentile": 0.8551282927155628, "raw_score": 0.5945509722287864, "significant": true}, {"trait_id": "facet_assertiveness", "name": "Assertiveness", "category": "personality", "percentile": 0.7314564698988347, "raw_score": 0.6749139496305445, "significant": true}, {"trait_id": "facet_cheerfulness", "name": "Cheerfulness", "category": "personality", "percentile": 0.0009193013298561814, "raw_score": 0.5135970468169622, "significant": true}, {"trait_id": "facet_excitement_seeking", "name": "Excitement-seeking", "category": "personality", "percentile": 0.049789200963690605, "raw_score": 0.5337755577825994, "significant": true}, {"trait_id": "facet_friendliness", "name": "Outgoing", "category": "personality", "percentile": 0.01241391194296676, "raw_score": 0.4479359906104231, "significant": true}, {"trait_id": "facet_gregariousness", "name": "Gregariousness", "category": "personality", "percentile": 0.001005634529824606, "raw_score": 0.2945587901068647, "significant": true}]}, {"trait_id": "big5_agreeableness", "name": "Agreeableness", "category": "personality", "percentile": 0.0008894326015991272, "raw_score": 0.6179707919786752, "significant": true, "children": [{"trait_id": "facet_altruism", "name": "Altruism", "category": "personality", "percentile": 0.3309261828617486, "raw_score": 0.6897466991933381, "significant": true}, {"trait_id": "facet_cooperation", "name": "Cooperation", "category": "personality", "percentile": 0.5689283859172585, "raw_score": 0.5898508951516788, "significant": true}, {"trait_id": "facet_modesty", "name": "Modesty", "category": "personality", "percentile": 0.37156920471872346, "raw_score": 0.4310840788925435, "significant": true}, {"trait_id": "facet_morality", "name": "Uncompromising", "category": "personality", "percentile": 0.45092642242797165, "raw_score": 0.6199921170029848, "significant": true}, {"trait_id": "facet_sympathy", "name": "Sympathy", "category": "personality", "percentile": 0.5290967430999112, "raw_score": 0.6662656387233333, "significant": true}, {"trait_id": "facet_trust", "name": "Trust", "category": "personality", "percentile": 0.622750301669674, "raw_score": 0.5986846628723528, "significant": true}]}, {"trait_id": "big5_neuroticism", "name": "Emotional range", "category": "personality", "percentile": 0.44318566297059947, "raw_score": 0.5311360603407861, "significant": true, "children": [{"trait_id": "facet_anger", "name": "Fiery", "category": "personality", "percentile": 0.5212786280200031, "raw_score": 0.5386337261504685, "significant": true}, {"trait_id": "facet_anxiety", "name": "Prone to worry", "category": "personality", "percentile": 0.28986360949784284, "raw_score": 0.5563454883648757, "significant": true}, {"trait_id": "facet_depression", "name": "Melancholy", "category": "personality", "percentile": 0.877702195840125, "raw_score": 0.5221375720880371, "significant": true}, {"trait_id": "facet_immoderation", "name": "Immoderation", "category": "personality", "percentile": 0.04987433989041684, "raw_score": 0.4373262698512206, "significant": true}, {"trait_id": "facet_self_consciousness", "name": "Self-consciousness", "category": "personality", "percentile": 0.90188328304428, "raw_score": 0.6147176386767887, "significant": true}, {"trait_id": "facet_vulnerability", "name": "Susceptible to stress", "category": "personality", "percentile": 0.45060124275865515, "raw_score": 0.4597125510080986, "significant": true}]}], "needs": [{"trait_id": "need_challenge", "name": "Challenge", "category": "needs", "percentile": 0.09273856291265065, "raw_score": 0.6724014017073221, "significant": true}, {"trait_id": "need_closeness", "name": "Closeness", "category": "needs", "percentile": 0.004427450096688268, "raw_score": 0.6771745812523885, "significant": true}, {"trait_id": "need_curiosity", "name": "Curiosity", "category": "needs", "percentile": 0.7032959416924491, "raw_score": 0.830702060436271, "significant": true}, {"trait_id": "need_excitement", "name": "Excitement", "category": "needs", "percentile": 0.09941914601096025, "raw_score": 0.5831408343951168, "significant": true}, {"trait_id": "need_harmony", "name": "Harmony", "category": "needs", "percentile": 0.004377420342514815, "raw_score": 0.7187375503879805, "significant": true}, {"trait_id": "need_ideal", "name": "Ideal", "category": "needs", "percentile": 0.09228801466968428, "raw_score": 0.6280024827108881, "significant": true}, {"trait_id": "need_liberty", "name": "Liberty", "category": "needs", "percentile": 0.20280682887312085, "raw_score": 0.7053568795311975, "significant": true}, {"trait_id": "need_love", "name": "Love", "category": "needs", "percentile": 0.0009738504022222538, "raw_score": 0.6179508796291073, "significant": true}, {"trait_id": "need_practicality", "name": "Practicality", "category": "needs", "percentile": 0.5467507487973351, "raw_score": 0.7303110215488706, "significant": true}, {"trait_id": "need_self_expression", "name": "Self-expression", "category": "needs", "percentile": 0.16470623054089417, "raw_score": 0.641395302775423, "significant": true}, {"trait_id": "need_stability", "name": "Stability", "category": "needs", "percentile": 0.022943967956719935, "raw_score": 0.6708689338255982, "significant": true}, {"trait_id": "need_structure", "name": "Structure", "category": "needs", "percentile": 0.6055491966305658, "raw_score": 0.7033333972529636, "significant": true}], "values": [{"trait_id": "value_conservation", "name": "Conservation", "category": "values", "percentile": 0.002303641115771693, "raw_score": 0.5378102775125224, "significant": true}, {"trait_id": "value_openness_to_change", "name": "Openness to change", "category": "values", "percentile": 0.3686886414208073, "raw_score": 0.7713374724247682, "significant": true}, {"trait_id": "value_hedonism", "name": "Hedonism", "category": "values", "percentile": 0.01450235439339892, "raw_score": 0.598671168002909, "significant": true}, {"trait_id": "value_self_enhancement", "name": "Self-enhancement", "category": "values", "percentile": 0.04146844779766318, "raw_score": 0.6302608474965725, "significant": true}, {"trait_id": "value_self_transcendence", "name": "Self-transcendence", "category": "values", "percentile": 0.09213683301656356, "raw_score": 0.8113333779309524, "significant": true}], "warnings": [{"warning_id": "JSON_AS_TEXT", "message": "Request input was processed as text/plain as indicated, however detected a JSON input. Did you mean application/json?"}]}